asynckapi/__init__.py
asynckapi_kal_byte-0.0.2.dist-info/LICENSE
asynckapi_kal_byte-0.0.2.dist-info/METADATA
asynckapi_kal_byte-0.0.2.dist-info/WHEEL
asynckapi_kal_byte-0.0.2.dist-info/top_level.txt
asynckapi_kal_byte-0.0.2.dist-info/RECORD
