Metadata-Version: 2.1
Name: asynckapi-kal-byte
Version: 0.0.2
Summary: A wrapper for my API.
Home-page: https://github.com/kal-byte/asynckapi
Author: kal-byte
License: UNKNOWN
Platform: UNKNOWN
Classifier: Programming Language :: Python :: 3
Classifier: License :: OSI Approved :: MIT License
Classifier: Operating System :: OS Independent
Requires-Python: >=3.6
